pyincore_viz/__init__.py
pyincore_viz/analysisviz.py
pyincore_viz/geoutil.py
pyincore_viz/globals.py
pyincore_viz/logging.ini
pyincore_viz/plotutil.py
pyincore_viz/tabledatasetlistmap.py
pyincore_viz/analysis/__init__.py
pyincore_viz/analysis/popresultstable.py
pyincore_viz/helpers/__init__.py
pyincore_viz/helpers/common.py
pyincore_viz-1.12.0.dist-info/licenses/LICENSE
pyincore_viz-1.12.0.dist-info/METADATA
pyincore_viz-1.12.0.dist-info/WHEEL
pyincore_viz-1.12.0.dist-info/top_level.txt
pyincore_viz-1.12.0.dist-info/RECORD
