Metadata-Version: 2.4
Name: pyincore_viz
Version: 1.12.0
Summary: IN-CORE visualization python package
Home-page: https://tools.in-core.org
License: Mozilla Public License v2.0
Project-URL: Bug Reports, https://github.com/IN-CORE/pyincor-vize/issues
Project-URL: Source, https://github.com/IN-CORE/pyincor-vize
Keywords: infrastructure,resilience,hazards,data discovery,IN-CORE,earthquake,tsunami,tornado,hurricane,dislocation
Classifier: Development Status :: 4 - Beta
Classifier: Intended Audience :: Science/Research
Classifier: License :: OSI Approved :: Mozilla Public License 2.0 (MPL 2.0)
Classifier: Natural Language :: English
Classifier: Operating System :: OS Independent
Classifier: Programming Language :: Python :: 3
Classifier: Topic :: Scientific/Engineering
License-File: LICENSE
Requires-Dist: branca>=0.3.0
Requires-Dist: contextily>=1.0.0
Requires-Dist: deprecated
Requires-Dist: geopandas>=0.14.0
Requires-Dist: ipyleaflet>=0.16.0
Requires-Dist: ipywidgets>=7.6.0
Requires-Dist: lxml>=4.6.3
Requires-Dist: matplotlib>=3.8.3
Requires-Dist: networkx>=3.2.1
Requires-Dist: numpy<2.0a0,>=1.26.0
Requires-Dist: owslib>=0.17.1
Requires-Dist: pandas>=2.1.2
Requires-Dist: pillow
Requires-Dist: pyincore>=1.20.0
Requires-Dist: rasterio>=1.3.9
Provides-Extra: test
Requires-Dist: pycodestyle>=2.6.0; extra == "test"
Requires-Dist: pytest>=3.9.0; extra == "test"
Requires-Dist: python-jose>=3.0; extra == "test"
Dynamic: classifier
Dynamic: description
Dynamic: description-content-type
Dynamic: home-page
Dynamic: keywords
Dynamic: license
Dynamic: license-file
Dynamic: project-url
Dynamic: provides-extra
Dynamic: requires-dist
Dynamic: summary
